[
  {
    "at": "2026-03-20T23:04:26.425Z",
    "runId": "4395e184-de01-4312-b426-c7daca252c4c",
    "cycles": 0,
    "promptsSent": 0,
    "successes": 0,
    "failures": 0,
    "contractFailures": 0,
    "parseFailures": 0,
    "actionsFound": 0,
    "lowValueCycles": 0,
    "dynamicFrequencySeconds": 45,
    "preflight": {
      "contractCheckMode": "unknown",
      "rawResponseShape": "unknown",
      "authVerdict": "unknown"
    }
  },
  {
    "at": "2026-03-20T23:04:26.881Z",
    "runId": "414e99a7-b673-4ca8-9ed6-311e1ed3ef6e",
    "cycles": 0,
    "promptsSent": 0,
    "successes": 0,
    "failures": 0,
    "contractFailures": 0,
    "parseFailures": 0,
    "actionsFound": 0,
    "lowValueCycles": 0,
    "dynamicFrequencySeconds": 45,
    "preflight": {
      "contractCheckMode": "unknown",
      "rawResponseShape": "unknown",
      "authVerdict": "unknown"
    }
  },
  {
    "at": "2026-03-20T23:05:21.982Z",
    "runId": "299e2d26-c1a5-4d69-9aa7-8dda13cb1727",
    "cycles": 0,
    "promptsSent": 0,
    "successes": 0,
    "failures": 1,
    "contractFailures": 1,
    "parseFailures": 0,
    "actionsFound": 0,
    "lowValueCycles": 0,
    "dynamicFrequencySeconds": 45,
    "preflight": {
      "contractCheckMode": "unknown",
      "rawResponseShape": "unknown",
      "authVerdict": "failed"
    }
  },
  {
    "at": "2026-03-20T23:05:32.750Z",
    "runId": "2b0d6c22-b1c7-4172-a64e-4d36df010f4f",
    "cycles": 0,
    "promptsSent": 0,
    "successes": 0,
    "failures": 1,
    "contractFailures": 1,
    "parseFailures": 0,
    "actionsFound": 0,
    "lowValueCycles": 0,
    "dynamicFrequencySeconds": 45,
    "preflight": {
      "contractCheckMode": "unknown",
      "rawResponseShape": "unknown",
      "authVerdict": "failed"
    }
  }
]