[{"conclusion":"","createdAt":"2026-04-29T22:32:58Z","status":"in_progress","url":"https://github.com/Zion-support/zion.app/actions/runs/25137332364","workflowName":"AI workflow failure triage hourly"},{"conclusion":"","createdAt":"2026-04-29T22:31:55Z","status":"in_progress","url":"https://github.com/Zion-support/zion.app/actions/runs/25137293226","workflowName":"AI GitHub workflow integrity audit (daily)"},{"conclusion":"failure","createdAt":"2026-04-29T22:30:39Z","status":"completed","url":"https://github.com/Zion-support/zion.app/actions/runs/25137246750","workflowName":"AI autonomous self-heal factory"},{"conclusion":"failure","createdAt":"2026-04-29T22:30:22Z","status":"completed","url":"https://github.com/Zion-support/zion.app/actions/runs/25137236307","workflowName":"AI lead form routing guard (daily)"},{"conclusion":"failure","createdAt":"2026-04-29T22:27:39Z","status":"completed","url":"https://github.com/Zion-support/zion.app/actions/runs/25137136225","workflowName":"Autonomous Writer Queue Guard"},{"conclusion":"failure","createdAt":"2026-04-29T22:27:13Z","status":"completed","url":"https://github.com/Zion-support/zion.app/actions/runs/25137121297","workflowName":"AI autonomous runtime guardian"},{"conclusion":"failure","createdAt":"2026-04-29T22:24:45Z","status":"completed","url":"https://github.com/Zion-support/zion.app/actions/runs/25137028088","workflowName":"AI Ultra-Fast Content"},{"conclusion":"failure","createdAt":"2026-04-29T22:24:43Z","status":"completed","url":"https://github.com/Zion-support/zion.app/actions/runs/25137027172","workflowName":"Autonomous Release Guardian"},{"conclusion":"skipped","createdAt":"2026-04-29T22:23:54Z","status":"completed","url":"https://github.com/Zion-support/zion.app/actions/runs/25136996064","workflowName":"AI Stale Promotion Re-promoter"},{"conclusion":"skipped","createdAt":"2026-04-29T22:23:54Z","status":"completed","url":"https://github.com/Zion-support/zion.app/actions/runs/25136995976","workflowName":"AI Stale Promotion Remediator"},{"conclusion":"skipped","createdAt":"2026-04-29T22:23:53Z","status":"completed","url":"https://github.com/Zion-support/zion.app/actions/runs/25136995622","workflowName":"AI Stale Promotion Remediator"},{"conclusion":"skipped","createdAt":"2026-04-29T22:23:53Z","status":"completed","url":"https://github.com/Zion-support/zion.app/actions/runs/25136995616","workflowName":"AI Stale Promotion Re-promoter"},{"conclusion":"skipped","createdAt":"2026-04-29T22:23:50Z","status":"completed","url":"https://github.com/Zion-support/zion.app/actions/runs/25136993871","workflowName":"Production Smoke Test"},{"conclusion":"skipped","createdAt":"2026-04-29T22:23:50Z","status":"completed","url":"https://github.com/Zion-support/zion.app/actions/runs/25136993869","workflowName":"AI Production Deploy Validation"},{"conclusion":"skipped","createdAt":"2026-04-29T22:23:50Z","status":"completed","url":"https://github.com/Zion-support/zion.app/actions/runs/25136993849","workflowName":"AI Stale Promotion Guard"},{"conclusion":"skipped","createdAt":"2026-04-29T22:23:49Z","status":"completed","url":"https://github.com/Zion-support/zion.app/actions/runs/25136993360","workflowName":"Production Smoke Test"},{"conclusion":"skipped","createdAt":"2026-04-29T22:23:49Z","status":"completed","url":"https://github.com/Zion-support/zion.app/actions/runs/25136993348","workflowName":"AI Stale Promotion Guard"},{"conclusion":"skipped","createdAt":"2026-04-29T22:23:49Z","status":"completed","url":"https://github.com/Zion-support/zion.app/actions/runs/25136993333","workflowName":"AI Production Deploy Validation"},{"conclusion":"failure","createdAt":"2026-04-29T22:23:24Z","status":"completed","url":"https://github.com/Zion-support/zion.app/actions/runs/25136978887","workflowName":"Monitoring Dashboard"},{"conclusion":"success","createdAt":"2026-04-29T22:22:23Z","status":"completed","url":"https://github.com/Zion-support/zion.app/actions/runs/25136942465","workflowName":"Autonomous Agent Parliament Execution"},{"conclusion":"failure","createdAt":"2026-04-29T22:22:23Z","status":"completed","url":"https://github.com/Zion-support/zion.app/actions/runs/25136942373","workflowName":"AI Content Rapid"},{"conclusion":"failure","createdAt":"2026-04-29T22:21:56Z","status":"completed","url":"https://github.com/Zion-support/zion.app/actions/runs/25136926251","workflowName":"Monitoring Dashboard & Alerts"},{"conclusion":"failure","createdAt":"2026-04-29T22:20:57Z","status":"completed","url":"https://github.com/Zion-support/zion.app/actions/runs/25136890114","workflowName":"AI lead gen contact route guard"},{"conclusion":"failure","createdAt":"2026-04-29T22:19:18Z","status":"completed","url":"https://github.com/Zion-support/zion.app/actions/runs/25136829149","workflowName":"AI Content Burst High Frequency"},{"conclusion":"failure","createdAt":"2026-04-29T22:17:03Z","status":"completed","url":"https://github.com/Zion-support/zion.app/actions/runs/25136749431","workflowName":"AI workflow trust regression guard"},{"conclusion":"skipped","createdAt":"2026-04-29T22:14:40Z","status":"completed","url":"https://github.com/Zion-support/zion.app/actions/runs/25136661422","workflowName":"AI Stale Promotion Re-promoter"},{"conclusion":"skipped","createdAt":"2026-04-29T22:14:40Z","status":"completed","url":"https://github.com/Zion-support/zion.app/actions/runs/25136661413","workflowName":"AI Stale Promotion Remediator"},{"conclusion":"skipped","createdAt":"2026-04-29T22:14:37Z","status":"completed","url":"https://github.com/Zion-support/zion.app/actions/runs/25136659906","workflowName":"Production Smoke Test"},{"conclusion":"skipped","createdAt":"2026-04-29T22:14:37Z","status":"completed","url":"https://github.com/Zion-support/zion.app/actions/runs/25136659903","workflowName":"AI Production Deploy Validation"},{"conclusion":"skipped","createdAt":"2026-04-29T22:14:37Z","status":"completed","url":"https://github.com/Zion-support/zion.app/actions/runs/25136659885","workflowName":"AI Stale Promotion Guard"},{"conclusion":"skipped","createdAt":"2026-04-29T22:14:34Z","status":"completed","url":"https://github.com/Zion-support/zion.app/actions/runs/25136657936","workflowName":"AI Build Fixer"},{"conclusion":"skipped","createdAt":"2026-04-29T22:14:34Z","status":"completed","url":"https://github.com/Zion-support/zion.app/actions/runs/25136657933","workflowName":"Deploy on Push"},{"conclusion":"skipped","createdAt":"2026-04-29T22:14:34Z","status":"completed","url":"https://github.com/Zion-support/zion.app/actions/runs/25136657918","workflowName":"AI CI Recovery"},{"conclusion":"success","createdAt":"2026-04-29T22:13:40Z","status":"completed","url":"https://github.com/Zion-support/zion.app/actions/runs/25136623869","workflowName":"CodeQL Security Analysis"},{"conclusion":"cancelled","createdAt":"2026-04-29T22:13:40Z","status":"completed","url":"https://github.com/Zion-support/zion.app/actions/runs/25136623866","workflowName":"Deploy on Push"},{"conclusion":"failure","createdAt":"2026-04-29T22:13:40Z","status":"completed","url":"https://github.com/Zion-support/zion.app/actions/runs/25136623864","workflowName":"Threat Matrix CI Integration"},{"conclusion":"failure","createdAt":"2026-04-29T22:13:40Z","status":"completed","url":"https://github.com/Zion-support/zion.app/actions/runs/25136623854","workflowName":"Autonomous Core Deployment Pipeline"},{"conclusion":"success","createdAt":"2026-04-29T22:13:40Z","status":"completed","url":"https://github.com/Zion-support/zion.app/actions/runs/25136623835","workflowName":"AI Smart Release Notes"},{"conclusion":"failure","createdAt":"2026-04-29T22:13:40Z","status":"completed","url":"https://github.com/Zion-support/zion.app/actions/runs/25136623830","workflowName":"AI App Improvement On Push"},{"conclusion":"success","createdAt":"2026-04-29T22:13:40Z","status":"completed","url":"https://github.com/Zion-support/zion.app/actions/runs/25136623828","workflowName":"AI Post Push Route Verify"},{"conclusion":"failure","createdAt":"2026-04-29T22:13:40Z","status":"completed","url":"https://github.com/Zion-support/zion.app/actions/runs/25136623812","workflowName":"Coverage Gate"},{"conclusion":"failure","createdAt":"2026-04-29T22:13:40Z","status":"completed","url":"https://github.com/Zion-support/zion.app/actions/runs/25136623811","workflowName":"AI Broken Link Fixer Agent"},{"conclusion":"failure","createdAt":"2026-04-29T22:13:40Z","status":"completed","url":"https://github.com/Zion-support/zion.app/actions/runs/25136623810","workflowName":"License Compliance Check"},{"conclusion":"","createdAt":"2026-04-29T22:13:40Z","status":"in_progress","url":"https://github.com/Zion-support/zion.app/actions/runs/25136623807","workflowName":"Deploy to GitHub Pages"},{"conclusion":"","createdAt":"2026-04-29T22:13:40Z","status":"in_progress","url":"https://github.com/Zion-support/zion.app/actions/runs/25136623803","workflowName":"Generate Changelog"},{"conclusion":"","createdAt":"2026-04-29T22:13:40Z","status":"in_progress","url":"https://github.com/Zion-support/zion.app/actions/runs/25136623796","workflowName":"Update Coverage Badge"},{"conclusion":"","createdAt":"2026-04-29T22:13:40Z","status":"in_progress","url":"https://github.com/Zion-support/zion.app/actions/runs/25136623788","workflowName":"CI/CD Pipeline"},{"conclusion":"failure","createdAt":"2026-04-29T22:13:39Z","status":"completed","url":"https://github.com/Zion-support/zion.app/actions/runs/25136622869","workflowName":".github/workflows/workflow-contracts-weekly.yml"},{"conclusion":"failure","createdAt":"2026-04-29T22:13:38Z","status":"completed","url":"https://github.com/Zion-support/zion.app/actions/runs/25136622305","workflowName":".github/workflows/workflow-validate-light-weekly.yml"},{"conclusion":"failure","createdAt":"2026-04-29T22:13:37Z","status":"completed","url":"https://github.com/Zion-support/zion.app/actions/runs/25136622073","workflowName":".github/workflows/workflow-audit-all.yml"},{"conclusion":"failure","createdAt":"2026-04-29T22:13:37Z","status":"completed","url":"https://github.com/Zion-support/zion.app/actions/runs/25136621400","workflowName":".github/workflows/ci-deploy.yml"},{"conclusion":"failure","createdAt":"2026-04-29T22:13:36Z","status":"completed","url":"https://github.com/Zion-support/zion.app/actions/runs/25136621199","workflowName":".github/workflows/ai-automation-orchestration.yml"},{"conclusion":"failure","createdAt":"2026-04-29T22:13:36Z","status":"completed","url":"https://github.com/Zion-support/zion.app/actions/runs/25136620988","workflowName":".github/workflows/workflow-yaml-sanity.yml"},{"conclusion":"failure","createdAt":"2026-04-29T22:13:35Z","status":"completed","url":"https://github.com/Zion-support/zion.app/actions/runs/25136620717","workflowName":".github/workflows/github_synchronizer.yml"},{"conclusion":"failure","createdAt":"2026-04-29T22:13:35Z","status":"completed","url":"https://github.com/Zion-support/zion.app/actions/runs/25136620498","workflowName":".github/workflows/generate-release-notes.yml"},{"conclusion":"failure","createdAt":"2026-04-29T22:13:35Z","status":"completed","url":"https://github.com/Zion-support/zion.app/actions/runs/25136620265","workflowName":".github/workflows/ai-actions-pin-strict-guard.yml"},{"conclusion":"failure","createdAt":"2026-04-29T22:13:34Z","status":"completed","url":"https://github.com/Zion-support/zion.app/actions/runs/25136619983","workflowName":".github/workflows/dependency-drift-guard-schedule.yml"},{"conclusion":"","createdAt":"2026-04-29T22:13:32Z","status":"in_progress","url":"https://github.com/Zion-support/zion.app/actions/runs/25136618623","workflowName":"Codespaces Prebuilds"},{"conclusion":"failure","createdAt":"2026-04-29T22:10:24Z","status":"completed","url":"https://github.com/Zion-support/zion.app/actions/runs/25136499625","workflowName":"AI GitHub integrity fix factory"},{"conclusion":"failure","createdAt":"2026-04-29T22:08:11Z","status":"completed","url":"https://github.com/Zion-support/zion.app/actions/runs/25136416744","workflowName":"AI Netlify Playwright smoke"},{"conclusion":"success","createdAt":"2026-04-29T22:03:36Z","status":"completed","url":"https://github.com/Zion-support/zion.app/actions/runs/25136244140","workflowName":"AI Smart Release Notes"},{"conclusion":"success","createdAt":"2026-04-29T22:03:36Z","status":"completed","url":"https://github.com/Zion-support/zion.app/actions/runs/25136244118","workflowName":"AI Post Push Route Verify"},{"conclusion":"failure","createdAt":"2026-04-29T22:03:36Z","status":"completed","url":"https://github.com/Zion-support/zion.app/actions/runs/25136244111","workflowName":"AI Broken Link Fixer Agent"},{"conclusion":"failure","createdAt":"2026-04-29T22:03:36Z","status":"completed","url":"https://github.com/Zion-support/zion.app/actions/runs/25136244110","workflowName":"Autonomous Core Deployment Pipeline"},{"conclusion":"cancelled","createdAt":"2026-04-29T22:03:36Z","status":"completed","url":"https://github.com/Zion-support/zion.app/actions/runs/25136244108","workflowName":"CI/CD Pipeline"},{"conclusion":"cancelled","createdAt":"2026-04-29T22:03:36Z","status":"completed","url":"https://github.com/Zion-support/zion.app/actions/runs/25136244107","workflowName":"Deploy on Push"},{"conclusion":"failure","createdAt":"2026-04-29T22:03:36Z","status":"completed","url":"https://github.com/Zion-support/zion.app/actions/runs/25136244106","workflowName":"Threat Matrix CI Integration"},{"conclusion":"failure","createdAt":"2026-04-29T22:03:36Z","status":"completed","url":"https://github.com/Zion-support/zion.app/actions/runs/25136244105","workflowName":"Coverage Gate"},{"conclusion":"failure","createdAt":"2026-04-29T22:03:36Z","status":"completed","url":"https://github.com/Zion-support/zion.app/actions/runs/25136244092","workflowName":"License Compliance Check"},{"conclusion":"success","createdAt":"2026-04-29T22:03:36Z","status":"completed","url":"https://github.com/Zion-support/zion.app/actions/runs/25136244090","workflowName":"CodeQL Security Analysis"},{"conclusion":"failure","createdAt":"2026-04-29T22:03:36Z","status":"completed","url":"https://github.com/Zion-support/zion.app/actions/runs/25136244087","workflowName":"Update Coverage Badge"},{"conclusion":"cancelled","createdAt":"2026-04-29T22:03:36Z","status":"completed","url":"https://github.com/Zion-support/zion.app/actions/runs/25136244086","workflowName":"Deploy to GitHub Pages"},{"conclusion":"failure","createdAt":"2026-04-29T22:03:36Z","status":"completed","url":"https://github.com/Zion-support/zion.app/actions/runs/25136244083","workflowName":"AI App Improvement On Push"},{"conclusion":"failure","createdAt":"2026-04-29T22:03:36Z","status":"completed","url":"https://github.com/Zion-support/zion.app/actions/runs/25136244082","workflowName":"Generate Changelog"},{"conclusion":"failure","createdAt":"2026-04-29T22:03:35Z","status":"completed","url":"https://github.com/Zion-support/zion.app/actions/runs/25136243459","workflowName":".github/workflows/ci-deploy.yml"},{"conclusion":"failure","createdAt":"2026-04-29T22:03:34Z","status":"completed","url":"https://github.com/Zion-support/zion.app/actions/runs/25136243090","workflowName":".github/workflows/dependency-drift-guard-schedule.yml"},{"conclusion":"failure","createdAt":"2026-04-29T22:03:34Z","status":"completed","url":"https://github.com/Zion-support/zion.app/actions/runs/25136242846","workflowName":".github/workflows/workflow-validate-light-weekly.yml"},{"conclusion":"failure","createdAt":"2026-04-29T22:03:33Z","status":"completed","url":"https://github.com/Zion-support/zion.app/actions/runs/25136242285","workflowName":".github/workflows/github_synchronizer.yml"},{"conclusion":"failure","createdAt":"2026-04-29T22:03:32Z","status":"completed","url":"https://github.com/Zion-support/zion.app/actions/runs/25136242078","workflowName":".github/workflows/generate-release-notes.yml"},{"conclusion":"failure","createdAt":"2026-04-29T22:03:32Z","status":"completed","url":"https://github.com/Zion-support/zion.app/actions/runs/25136241884","workflowName":".github/workflows/workflow-yaml-sanity.yml"}]
