{
  "timestamp": "2025-09-04T02:58:25.517Z",
  "duration": "1ms",
  "overallStatus": "warning",
  "summary": {
    "total": 7,
    "healthy": 5,
    "warnings": 2,
    "unhealthy": 0
  },
  "checks": [
    {
      "name": "File System",
      "status": "healthy",
      "details": "File system accessible"
    },
    {
      "name": "Node.js Version",
      "status": "healthy",
      "details": "Node.js v22.16.0 (compatible)"
    },
    {
      "name": "Package.json",
      "status": "healthy",
      "details": "Package: ziontechgroup.com v0.1.0"
    },
    {
      "name": "Dependencies",
      "status": "warning",
      "details": "node_modules not found, run npm install"
    },
    {
      "name": "Build System",
      "status": "healthy",
      "details": "Next.js configuration found"
    },
    {
      "name": "Source Files",
      "status": "healthy",
      "details": "Required directories present"
    },
    {
      "name": "Environment",
      "status": "warning",
      "details": "Missing environment variables: NODE_ENV"
    }
  ]
}