{
  "id": "service-1755574949752-w2vvoioe0",
  "category": "Blockchain Solutions",
  "template": "aiService",
  "title": "AI-Powered Blockchain Solutions Service",
  "description": "Advanced Blockchain Solutions solution powered by cutting-edge artificial intelligence",
  "features": [
    "Intelligent automation and optimization",
    "Real-time data processing and analysis",
    "Scalable cloud infrastructure",
    "Advanced security and compliance",
    "24/7 monitoring and support"
  ],
  "pricing": [
    {
      "plan": "Starter",
      "price": "$99/month",
      "features": [
        "Basic features",
        "Email support"
      ]
    },
    {
      "plan": "Professional",
      "price": "$299/month",
      "features": [
        "Advanced features",
        "Priority support",
        "Custom integrations"
      ]
    },
    {
      "plan": "Enterprise",
      "price": "Custom",
      "features": [
        "Full customization",
        "Dedicated support",
        "SLA guarantee"
      ]
    }
  ],
  "createdAt": "2025-08-19T03:42:29.752Z",
  "status": "active",
  "metadata": {
    "generatedBy": "ultra-fast-service-generator",
    "version": "1.0.0",
    "priority": "high"
  }
}